{
    "id":"recJHFZYaWVLJihcP",
    "title":"SEO Gets You Found, AEO Gets You Named: Why Answer Engine Optimization Is Your Next Competitive…",
    "slug":"seo-vs-aeo-guide-2025-134ff6d9824e",
    "folder": "2025-08-13-seo-vs-aeo-guide-2025-134ff6d9824e",
    "published_date": "2025-08-13",
    "author": "Dr. Hernani Costa",
    "author_url": "https://drhernanicosta.com",
    "company": "First AI Movers",
    "company_url": "https://firstaimovers.com",
    "canonical_url": "https://insights.firstaimovers.com/seo-vs-aeo-guide-2025-134ff6d9824e",
    "tags":["AI answer optimization strategies","SEO vs AEO for SMEs","future of digital visibility","AI-generated content citation","personal branding in AI era","conversational content structure"],
    "word_count": 2630,
    "read_time_minutes":12,
    "funnel_stage": "middle",
    "first_ai_movers_services": [],
    "status": "published"
}