{
    "id":"recfsHo6JnS3ycWtQ",
    "title":"AI Industry Trends 2025: Multi-Perspective Insights & Strategies to Adapt",
    "slug":"ai-industry-trends-2025-multi-perspective-insights-strategies-to-adapt-fbc9ffae80a8",
    "folder": "2025-02-18-ai-industry-trends-2025-multi-perspective-insights-stra",
    "published_date": "2025-02-18",
    "author": "Dr. Hernani Costa",
    "author_url": "https://drhernanicosta.com",
    "company": "First AI Movers",
    "company_url": "https://firstaimovers.com",
    "canonical_url": "https://insights.firstaimovers.com/ai-industry-trends-2025-multi-perspective-insights-strategies-to-adapt-fbc9ffae80a8",
    "tags":["AI industry trends 2025","EU AI Act compliance","AI governance for European SMEs","AI adoption strategies","emerging AI technologies","startup innovation in AI","enterprise AI transformation"],
    "word_count": 2765,
    "read_time_minutes":13,
    "funnel_stage": "top",
    "first_ai_movers_services": [],
    "status": "published"
}