{
  "id": "recGqG8lfYjnkEdVu",
  "title": "AI Consulting for Milan's Fintech and Professional Services SMEs in 2026",
  "slug": "ai-consulting-milan-fintech-smes-2026",
  "folder": "2026-04-17-ai-consulting-milan-fintech-smes-2026",
  "published_date": "2026-04-17",
  "author": "Dr. Hernani Costa",
  "author_url": "https://drhernanicosta.com",
  "company": "First AI Movers",
  "company_url": "https://firstaimovers.com",
  "canonical_url": "https://radar.firstaimovers.com/ai-consulting-milan-fintech-smes-2026",
  "tags": [
    "AI consulting for SMEs",
    "Milan fintech landscape",
    "EU AI Act compliance",
    "Italian regulatory environment",
    "AI governance for SMEs",
    "AI tool selection",
    "AI literacy training"
  ],
  "word_count": 1745,
  "read_time_minutes": 8,
  "funnel_stage": "middle",
  "first_ai_movers_services": [],
  "status": "published",
  "topics": [
    "European SME AI",
    "AI Consulting",
    "Fintech AI",
    "Italy AI",
    "EU AI Act",
    "AI Governance"
  ]
}
